naturalspeech2_pytorch/__init__.py
naturalspeech2_pytorch/aligner.py
naturalspeech2_pytorch/attend.py
naturalspeech2_pytorch/naturalspeech2_pytorch.py
naturalspeech2_pytorch/version.py
naturalspeech2_pytorch/utils/__init__.py
naturalspeech2_pytorch/utils/cleaner.py
naturalspeech2_pytorch/utils/tokenizer.py
naturalspeech2_pytorch/utils/utils.py
naturalspeech2_pytorch/utils/expand/__init__.py
naturalspeech2_pytorch/utils/expand/abbreviations.csv
naturalspeech2_pytorch/utils/expand/abbreviations.py
naturalspeech2_pytorch/utils/expand/number_norm.py
naturalspeech2_pytorch/utils/expand/time_norm.py
naturalspeech2_pytorch/utils/phonemizers/__init__.py
naturalspeech2_pytorch/utils/phonemizers/base.py
naturalspeech2_pytorch/utils/phonemizers/espeak_wrapper.py
naturalspeech2_pytorch/utils/phonemizers/punctuation.py
naturalspeech2_pytorch-0.1.8.dist-info/LICENSE
naturalspeech2_pytorch-0.1.8.dist-info/METADATA
naturalspeech2_pytorch-0.1.8.dist-info/WHEEL
naturalspeech2_pytorch-0.1.8.dist-info/top_level.txt
naturalspeech2_pytorch-0.1.8.dist-info/RECORD
