Metadata-Version: 2.1
Name: naturalspeech2-pytorch
Version: 0.1.8
Summary: Natural Speech 2 - Pytorch
Home-page: https://github.com/lucidrains/naturalspeech2-pytorch
Author: Phil Wang
Author-email: lucidrains@gmail.com
License: MIT
Keywords: artificial intelligence,deep learning,latent diffusion,speech synthesis
Classifier: Development Status :: 4 - Beta
Classifier: Intended Audience :: Developers
Classifier: Topic :: Scientific/Engineering :: Artificial Intelligence
Classifier: License :: OSI Approved :: MIT License
Classifier: Programming Language :: Python :: 3.6
License-File: LICENSE
Requires-Dist: accelerate
Requires-Dist: audiolm-pytorch >=0.30.2
Requires-Dist: beartype
Requires-Dist: einops >=0.6.1
Requires-Dist: ema-pytorch
Requires-Dist: indic-num2words
Requires-Dist: inflect
Requires-Dist: local-attention
Requires-Dist: num2words
Requires-Dist: pyworld
Requires-Dist: pydantic <2.0
Requires-Dist: torch >=1.6
Requires-Dist: tqdm
Requires-Dist: vector-quantize-pytorch >=1.4.1
